pyconsole/__init__.py
pyconsole/color.py
pyconsole/color_parser.py
pyconsole/color_traceback.py
pyconsole/colorwrap.py
pyconsole/console.py
pyconsole/errors.py
pyconsole/functions.py
pyconsole/global_data.py
pyconsole/keyboard.py
pyconsole/pretty.py
pyconsole/table.py
python_console-1.3.2.dist-info/LICENSE
python_console-1.3.2.dist-info/METADATA
python_console-1.3.2.dist-info/WHEEL
python_console-1.3.2.dist-info/top_level.txt
python_console-1.3.2.dist-info/RECORD
