Metadata-Version: 2.1
Name: python-console
Version: 1.3.2
Summary: A (basic) cross-platform python console manager
Home-page: https://github.com/DaHunterTime/PyConsole
Author: DaHunterTime
License: MIT
Project-URL: Bug Tracker, https://github.com/DaHunterTime/PyConsole/issues
Classifier: Programming Language :: Python :: 3
Classifier: License :: OSI Approved :: MIT License
Classifier: Operating System :: OS Independent
Requires-Python: >=3.8
License-File: LICENSE
Requires-Dist: pyinputhandler (>=1.3.0)
